thai_tokenizer/__init__.py
thai_tokenizer/__main__.py
thai_tokenizer/loader.py
thai_tokenizer/preprocessor.py
thai_tokenizer/tcc.py
thai_tokenizer/tokenizer.py
thai_tokenizer/trainer.py
thai_tokenizer/data/__init__.py
thai_tokenizer/data/bpe_merges.jsonl
thai_tokenizer-0.2.5.dist-info/LICENSE.txt
thai_tokenizer-0.2.5.dist-info/METADATA
thai_tokenizer-0.2.5.dist-info/WHEEL
thai_tokenizer-0.2.5.dist-info/top_level.txt
thai_tokenizer-0.2.5.dist-info/zip-safe
thai_tokenizer-0.2.5.dist-info/RECORD
