Metadata-Version: 2.1
Name: thai-tokenizer
Version: 0.2.5
Summary: Fast and accurate Thai tokenization library.
Home-page: https://github.com/IDDT/thai-tokenizer
Author: Kirill Orlov
Author-email: IDDT@users.noreply.github.com
License: MIT
Keywords: thai,tokenizer
Platform: UNKNOWN
Classifier: Development Status :: 2 - Pre-Alpha
Classifier: Programming Language :: Python :: 3.6
Classifier: Programming Language :: Python :: 3.7
Classifier: Programming Language :: Python :: 3.8
Classifier: Programming Language :: Python :: 3.9
Classifier: Intended Audience :: Developers
Classifier: License :: OSI Approved :: MIT License
Classifier: Natural Language :: Thai
Classifier: Operating System :: OS Independent
Classifier: Topic :: Text Processing :: Linguistic
Requires-Python: >=3.6
